TGFaceRecognition/__init__.py
TGFaceRecognition/faceRecognitionFromCameraLL - ÉRÉsÅ[.py
TGPKU_FaceRecognition-0.0.2.dist-info/DESCRIPTION.rst
TGPKU_FaceRecognition-0.0.2.dist-info/METADATA
TGPKU_FaceRecognition-0.0.2.dist-info/RECORD
TGPKU_FaceRecognition-0.0.2.dist-info/WHEEL
TGPKU_FaceRecognition-0.0.2.dist-info/metadata.json
TGPKU_FaceRecognition-0.0.2.dist-info/top_level.txt
