Metadata-Version: 2.0
Name: TGPKU-FaceRecognition
Version: 0.0.2
Summary: Designed to make Face Recognition easier
Home-page: https://github.com/pypa/example-project
Author: LongTianbao
Author-email: longtianbao@gmail.com
License: UNKNOWN
Platform: UNKNOWN
Classifier: Programming Language :: Python :: 3
Classifier: License :: OSI Approved :: MIT License
Classifier: Operating System :: OS Independent
